llmtranslator/__init__.py
llmtranslator/cli.py
llmtranslator/llmtranslator.py
llmtranslator/longtext.py
llmtranslator/mdtext.py
llmtranslator/process_files.py
llmtranslator-0.0.1.dist-info/LICENSE
llmtranslator-0.0.1.dist-info/METADATA
llmtranslator-0.0.1.dist-info/WHEEL
llmtranslator-0.0.1.dist-info/entry_points.txt
llmtranslator-0.0.1.dist-info/top_level.txt
llmtranslator-0.0.1.dist-info/RECORD
