Metadata-Version: 2.1
Name: llmtranslator
Version: 0.0.1
Summary: Text translator using OpenAI-like API.
Home-page: https://github.com/RexWzh/llmtranslator
Author: Rex Wang
Author-email: 1073853456@qq.com
License: MIT license
Keywords: llmtranslator
Classifier: Development Status :: 2 - Pre-Alpha
Classifier: Intended Audience :: Developers
Classifier: License :: OSI Approved :: MIT License
Classifier: Natural Language :: English
Classifier: Programming Language :: Python :: 3.7
Classifier: Programming Language :: Python :: 3.8
Classifier: Programming Language :: Python :: 3.9
Requires-Python: >=3.6
License-File: LICENSE
Requires-Dist: chattool (>=2.0)
